pywebidl2/__init__.py
pywebidl2/__main__.py
pywebidl2/exceptions.py
pywebidl2/expr.py
pywebidl2/generated/WebIDLLexer.interp
pywebidl2/generated/WebIDLLexer.py
pywebidl2/generated/WebIDLLexer.tokens
pywebidl2/generated/WebIDLParser.interp
pywebidl2/generated/WebIDLParser.py
pywebidl2/generated/WebIDLParser.tokens
pywebidl2/generated/WebIDLParserVisitor.py
pywebidl2/generated/__init__.py
pywebidl2/idl.py
pywebidl2/main.py
pywebidl2/parser.py
pywebidl2/py.typed
pywebidl2/utils.py
pywebidl2/visitor.py
pywebidl2-0.1.7.dist-info/LICENSE
pywebidl2-0.1.7.dist-info/WHEEL
pywebidl2-0.1.7.dist-info/METADATA
pywebidl2-0.1.7.dist-info/RECORD
