Metadata-Version: 2.1
Name: pywebidl2
Version: 0.1.7
Summary: WebIDL tool
Home-page: https://github.com/PrVrSs/pywebidl2
License: MIT
Keywords: WebIDL,parser,ast
Author: Sergey Reshetnikov
Author-email: resh.sersh@gmail.com
Requires-Python: >=3.10,<4.0
Classifier: License :: OSI Approved :: MIT License
Classifier: Programming Language :: Python :: 3
Classifier: Programming Language :: Python :: 3.10
Requires-Dist: antlr4-python3-runtime (==4.11.1)
Requires-Dist: click (>=8.1.3,<9.0.0)
Requires-Dist: more-itertools (>=8.14.0,<9.0.0)
Requires-Dist: stringcase (>=1.2.0,<2.0.0)
Project-URL: Repository, https://github.com/PrVrSs/pywebidl2
